neutron_fwaas/__init__.py
neutron_fwaas/_i18n.py
neutron_fwaas/opts.py
neutron_fwaas/version.py
neutron_fwaas/cmd/__init__.py
neutron_fwaas/cmd/upgrade_checks/__init__.py
neutron_fwaas/cmd/upgrade_checks/checks.py
neutron_fwaas/common/__init__.py
neutron_fwaas/common/exceptions.py
neutron_fwaas/common/fwaas_constants.py
neutron_fwaas/common/resources.py
neutron_fwaas/db/__init__.py
neutron_fwaas/db/firewall/__init__.py
neutron_fwaas/db/firewall/v2/__init__.py
neutron_fwaas/db/firewall/v2/firewall_db_v2.py
neutron_fwaas/db/migration/__init__.py
neutron_fwaas/db/migration/alembic_migrations/README
neutron_fwaas/db/migration/alembic_migrations/__init__.py
neutron_fwaas/db/migration/alembic_migrations/env.py
neutron_fwaas/db/migration/alembic_migrations/script.py.mako
neutron_fwaas/db/migration/alembic_migrations/versions/4202e3047e47_add_index_tenant_id.py
neutron_fwaas/db/migration/alembic_migrations/versions/540142f314f4_fwaas_router_insertion.py
neutron_fwaas/db/migration/alembic_migrations/versions/796c68dffbb_cisco_csr_fwaas.py
neutron_fwaas/db/migration/alembic_migrations/versions/CONTRACT_HEAD
neutron_fwaas/db/migration/alembic_migrations/versions/EXPAND_HEAD
neutron_fwaas/db/migration/alembic_migrations/versions/kilo_release.py
neutron_fwaas/db/migration/alembic_migrations/versions/start_neutron_fwaas.py
neutron_fwaas/db/migration/alembic_migrations/versions/2023.2/expand/6941ce70131e_add_standard_attr_id.py
neutron_fwaas/db/migration/alembic_migrations/versions/2025.1/contract/1007f519ea46_drop_v1.py
neutron_fwaas/db/migration/alembic_migrations/versions/2025.1/expand/2a0d33e9ef63_add_pk_firewall_group_associations_v2.py
neutron_fwaas/db/migration/alembic_migrations/versions/liberty/contract/67c8e8d61d5_initial.py
neutron_fwaas/db/migration/alembic_migrations/versions/liberty/expand/4b47ea298795_add_reject_rule.py
neutron_fwaas/db/migration/alembic_migrations/versions/liberty/expand/c40fbb377ad_initial.py
neutron_fwaas-23.0.0.dist-info/AUTHORS
neutron_fwaas-23.0.0.dist-info/LICENSE
neutron_fwaas-23.0.0.dist-info/METADATA
neutron_fwaas-23.0.0.dist-info/WHEEL
neutron_fwaas-23.0.0.dist-info/entry_points.txt
neutron_fwaas-23.0.0.dist-info/pbr.json
neutron_fwaas-23.0.0.dist-info/top_level.txt
neutron_fwaas-23.0.0.dist-info/RECORD
